{
"type": "FeatureCollection",
"crs": { "type": "name", "properties": { "name": "urn:ogc:def:crs:OGC:1.3:CRS84" } },
                                                                                
"features": [
{ "type": "Feature", "properties": { "antenna height": 2.000000, "lateral rms": 0.003500, "name": "Point SW", "projected mean": "-112.703825456 52.3176660209 799.042152941", "rms": "0.00126915901344 0.0032847809571 0.00523463521128", "sample count": 17.000000, "solution status": "FLOAT" }, "geometry": { "type": "Point", "coordinates": [ -112.703825456058837, 52.317666020941175, 799.042152941176596 ] } },
{ "type": "Feature", "properties": { "antenna height": 2.000000, "lateral rms": 0.000100, "name": "Point 2", "projected mean": "-112.703831819 52.3176664518 799.3206125", "rms": "0.000142642689639 -3.20164952526e-11 0.000164207555928", "sample count": 8.000000, "solution status": "FIX" }, "geometry": { "type": "Point", "coordinates": [ -112.703831819, 52.31766645175, 799.320612499999925 ] } }
]
}
