{
"type": "FeatureCollection",
"crs": { "type": "name", "properties": { "name": "urn:ogc:def:crs:OGC:1.3:CRS84" } },
                                                                                
"features": [
{ "type": "Feature", "properties": { "antenna height": 2.000000, "lateral rms": 0.002700, "name": "Point 1", "projected mean": "-112.885231475 52.4598656216 770.05233617", "rms": "0.00244933195627 0.00114306714337 0.00473829967937", "sample count": 47.000000, "solution status": "FIX" }, "geometry": { "type": "Point", "coordinates": [ -112.885231474510661, 52.459865621574458, 770.052336170212698 ] } },
{ "type": "Feature", "properties": { "antenna height": 2.000000, "lateral rms": 0.001700, "name": "Point 2", "projected mean": "-112.885231463 52.4598656199 770.04615614", "rms": "0.00153541718057 0.000839392046499 0.00421815900731", "sample count": 57.000000, "solution status": "FIX" }, "geometry": { "type": "Point", "coordinates": [ -112.885231463035069, 52.459865619894764, 770.046156140350718 ] } },
{ "type": "Feature", "properties": { "antenna height": 2.000000, "lateral rms": 0.089000, "name": "Point 3", "projected mean": "-112.884677504 52.4601217176 763.883638462", "rms": "0.0494440172082 0.0740604949339 0.116622574305", "sample count": 26.000000, "solution status": "FLOAT" }, "geometry": { "type": "Point", "coordinates": [ -112.884677504346158, 52.460121717615394, 763.883638461538453 ] } },
{ "type": "Feature", "properties": { "antenna height": 2.000000, "lateral rms": 0.082100, "name": "Point 4", "projected mean": "-112.884636963 52.4602704717 760.902217391", "rms": "0.0384627946084 0.0725176539314 0.089729049515", "sample count": 23.000000, "solution status": "FLOAT" }, "geometry": { "type": "Point", "coordinates": [ -112.884636962956534, 52.460270471695651, 760.902217391304362 ] } },
{ "type": "Feature", "properties": { "antenna height": 2.000000, "lateral rms": 0.000200, "name": "Point 5", "projected mean": "-112.884652089 52.4602754547 760.53088", "rms": "0.000123831847734 0.00012322310397 0.000618985026743", "sample count": 15.000000, "solution status": "FIX" }, "geometry": { "type": "Point", "coordinates": [ -112.884652089000014, 52.460275454666672, 760.530879999999797 ] } },
{ "type": "Feature", "properties": { "antenna height": 2.000000, "lateral rms": 0.000100, "name": "Point 6", "projected mean": "-112.884652067 52.460275425 760.518042857", "rms": "-5.12110815586e-11 0.000101699574089 5.34517958772e-05", "sample count": 7.000000, "solution status": "FIX" }, "geometry": { "type": "Point", "coordinates": [ -112.8846520672857, 52.460275425, 760.518042857142859 ] } },
{ "type": "Feature", "properties": { "antenna height": 2.000000, "lateral rms": 0.291700, "name": "Point 7", "projected mean": "-112.884581115 52.4602469296 761.288421429", "rms": "0.204445307313 0.208036897308 0.0268778709374", "sample count": 14.000000, "solution status": "FLOAT" }, "geometry": { "type": "Point", "coordinates": [ -112.884581114857156, 52.460246929571426, 761.288421428571496 ] } },
{ "type": "Feature", "properties": { "antenna height": 2.000000, "lateral rms": 0.261500, "name": "Point 8", "projected mean": "-112.884559945 52.4602040979 761.104335294", "rms": "0.0372992448827 0.258790060387 0.00309756242594", "sample count": 17.000000, "solution status": "FLOAT" }, "geometry": { "type": "Point", "coordinates": [ -112.884559945411752, 52.460204097882354, 761.104335294117504 ] } },
{ "type": "Feature", "properties": { "antenna height": 2.000000, "lateral rms": 0.111400, "name": "Point 9", "projected mean": "-112.885282645 52.4599632351 768.81206", "rms": "0.0440145065148 0.102297092509 0.26764716657", "sample count": 20.000000, "solution status": "FLOAT" }, "geometry": { "type": "Point", "coordinates": [ -112.885282644650019, 52.459963235149999, 768.81206 ] } },
{ "type": "Feature", "properties": { "antenna height": 2.000000, "lateral rms": 0.003800, "name": "Point 10", "projected mean": "-112.885279584 52.459956691 770.176945455", "rms": "0.00215166101412 0.00315523986695 0.0100914191927", "sample count": 11.000000, "solution status": "FIX" }, "geometry": { "type": "Point", "coordinates": [ -112.885279583545469, 52.459956691, 770.176945454545375 ] } }
]
}
